Workbook

Sheet Pesca Nacional
A1: CLIENTES NACIONALES | B1: INFORMACIÓN GENERAL | T1: STATUS PAGO PROGRAMA | AE1: DETALLE DE PAGOS
B2: CLIENTE | E2: DETALLE PROGRAMA | K2: DESCUENTO | T2: SEGUIMIENTO RESERVA | Y2: SEGUIMIENTO SALDO | AD2: PAGO 1 | AH2: PAGO 2 | AL2: PAGO 3 | AP2: PAGO 4 | AT2: PAGO 5
A3: Reserva N˚ | B3: Grupo | C3: Nombre | D3: Email | E3: Programa | F3: Noches | G3: Fecha Reserva | H3: Check-In | I3: Check-Out | J3: Precio lista | K3: ¿Es operador? | L3: V˚B˚ | M3: Modo | N3: Descuento ingresado | O3: Dscto (%) | P3: Dscto ($) | Q3: Valor Bruto | R3: Valor Líquido | T3: Estado reserva | U3: Monto total reserva | V3: Pagado a la fecha reserva | W3: Adeudado a la fecha reserva | X3: Adeudado grupal reserva | Y3: Estado saldo | Z3: Monto total saldo | AA3: Pagado a la fecha saldo | AB3: Adeudado a la fecha saldo | AC3: Adeudado grupal saldo | AD3: Concepto Pago 1 | AE3: Fecha Pago 1 | AF3: Monto Pago 1 | AG3: Medio de pago Pago 1 | AH3: Concepto Pago 2 | AI3: Fecha Pago 2 | AJ3: Monto Pago 2 | AK3: Medio de pago Pago 2 | AL3: Concepto Pago 3 | AM3: Fecha Pago 3 | AN3: Monto Pago 3 | AO3: Medio de pago Pago 3 | AP3: Concepto Pago 4 | AQ3: Fecha Pago 4 | AR3: Monto Pago 4 | AS3: Medio de pago Pago 4 | AT3: Concepto Pago 5 | AU3: Fecha Pago 5 | AV3: Monto Pago 5 | AW3: Medio de pago Pago 5 | BR3: Programa_texto | BS3: Días desde reserva | BT3: Días para check-in | BU3: GBL25
A4: {=IF(B4="","","Grupo N˚"&SUMPRODUCT(($B$4:B4<>"")*($B$4:B4<>OFFSET($B$4,-1,0,ROWS($B$4:B4),1))))} | I4: =+IF(H4="","",G4+H4) | J4: =IFERROR(VLOOKUP(BR4,Pricing!$D$3:$E$58,2,FALSE),"") | N4: {=IFERROR(_xlfn.IFS((AND(K4="SI",M4="$")),J4*0.2,AND(K4="SI",M4="%"),20),"")} | O4: =IFERROR(IF($M4="%", IF(N(N4)>1, N(N4)/100, N(N4)), IF(AND($J4>0,$M4="$"), N(N4)/$J4, "") ),"") | P4: =IFERROR(IF(M4="$", N(N4), IF(M4="%", J4*N(N4/100), "")), "") | Q4: =IF(J4="","",J4*(1-N(O4))) | R4: =IF(Q4="","",Q4/1.19) | T4: =IF(W4="","",IFERROR( IF(AND(ABS(N(W4))<0.5, BS4<=7), "Sin deuda", IF(AND(N(W4)>0, BS4<=7), "Con deuda", IF(AND(N(W4)>0, BS4>7), "Moroso", "") ) )," ")) | U4: =IF(R4="","",R4/2) | V4: =IF(AD4="","",SUM( IF(ISNUMBER(SEARCH("reserva",AD4)),AF4,0), IF(ISNUMBER(SEARCH("reserva",AH4)),AJ4,0), IF(ISNUMBER(SEARCH("reserva",AL4)),AN4,0), IF(ISNUMBER(SEARCH("reserva",AP4)),AR4,0), IF(ISNUMBER(SEARCH("reserva",AT4)),AV4,0) )) | W4: =IFERROR(U4-N(V4),"") | X4: =IF(W4="","",SUMIF($B$4:$B$1002,B4,$W$4:$W$1000)) | Y4: =IF(AB4="","",IFERROR( IF(AND(ABS(N(AB4))<0.5, BT4>=23), "Sin deuda", IF(AND(N(AB4)>0, BT4>=23), "Con deuda", IF(AND(N(AB4)>0, BT4<23), "Moroso", "") ) ),"")) | Z4: =IF(R4="","",R4/2) | AA4: =IF(AD4="","",SUM( IF(ISNUMBER(SEARCH("saldo",AD4)),AF4,0), IF(ISNUMBER(SEARCH("saldo",AH4)),AJ4,0), IF(ISNUMBER(SEARCH("saldo",AL4)),AN4,0), IF(ISNUMBER(SEARCH("saldo",AP4)),AR4,0), IF(ISNUMBER(SEARCH("saldo",AT4)),AV4,0) )) | AB4: =IFERROR(Z4-N(AA4),"") | AC4: =IF(AB4="","",SUMIF($B$4:$B$1002,B4,$AB$4:$AB$1000)) | BR4: =IF(E4="","",CONCATENATE(E4," ",F4," noches")) | BS4: =IF(G4="","",+TODAY()-G4) | BT4: =IF(H4="","",H4-TODAY())
A5: {=IF(B5="","","Grupo N˚"&SUMPRODUCT(($B$4:B5<>"")*($B$4:B5<>OFFSET($B$4,-1,0,ROWS($B$4:B5),1))))} | I5: =+IF(H5="","",G5+H5) | J5: =IFERROR(VLOOKUP(BR5,Pricing!$D$3:$E$58,2,FALSE),"") | N5: {=IFERROR(_xlfn.IFS((AND(K5="SI",M5="$")),J5*0.2,AND(K5="SI",M5="%"),20),"")} | O5: =IFERROR(IF($M5="%", IF(N(N5)>1, N(N5)/100, N(N5)), IF(AND($J5>0,$M5="$"), N(N5)/$J5, "") ),"") | P5: =IFERROR(IF(M5="$", N(N5), IF(M5="%", J5*N(N5/100), "")), "") | Q5: =IF(J5="","",J5*(1-N(O5))) | R5: =IF(Q5="","",Q5/1.19) | T5: =IF(W5="","",IFERROR( IF(AND(ABS(N(W5))<0.5, BS5<=7), "Sin deuda", IF(AND(N(W5)>0, BS5<=7), "Con deuda", IF(AND(N(W5)>0, BS5>7), "Moroso", "") ) )," ")) | U5: =IF(R5="","",R5/2) | V5: =IF(AD5="","",SUM( IF(ISNUMBER(SEARCH("reserva",AD5)),AF5,0), IF(ISNUMBER(SEARCH("reserva",AH5)),AJ5,0), IF(ISNUMBER(SEARCH("reserva",AL5)),AN5,0), IF(ISNUMBER(SEARCH("reserva",AP5)),AR5,0), IF(ISNUMBER(SEARCH("reserva",AT5)),AV5,0) )) | W5: =IFERROR(U5-N(V5),"") | X5: =IF(W5="","",SUMIF($B$4:$B$1002,B5,$W$4:$W$1000)) | Y5: =IF(AB5="","",IFERROR( IF(AND(ABS(N(AB5))<0.5, BT5>=23), "Sin deuda", IF(AND(N(AB5)>0, BT5>=23), "Con deuda", IF(AND(N(AB5)>0, BT5<23), "Moroso", "") ) ),"")) | Z5: =IF(R5="","",R5/2) | AA5: =IF(AD5="","",SUM( IF(ISNUMBER(SEARCH("saldo",AD5)),AF5,0), IF(ISNUMBER(SEARCH("saldo",AH5)),AJ5,0), IF(ISNUMBER(SEARCH("saldo",AL5)),AN5,0), IF(ISNUMBER(SEARCH("saldo",AP5)),AR5,0), IF(ISNUMBER(SEARCH("saldo",AT5)),AV5,0) )) | AB5: =IFERROR(Z5-N(AA5),"") | AC5: =IF(AB5="","",SUMIF($B$4:$B$1002,B5,$AB$4:$AB$1000)) | BR5: =IF(E5="","",CONCATENATE(E5," ",F5," noches")) | BS5: =IF(G5="","",+TODAY()-G5) | BT5: =IF(H5="","",H5-TODAY())
A6: {=IF(B6="","","Grupo N˚"&SUMPRODUCT(($B$4:B6<>"")*($B$4:B6<>OFFSET($B$4,-1,0,ROWS($B$4:B6),1))))} | I6: =+IF(H6="","",G6+H6) | J6: =IFERROR(VLOOKUP(BR6,Pricing!$D$3:$E$58,2,FALSE),"") | N6: {=IFERROR(_xlfn.IFS((AND(K6="SI",M6="$")),J6*0.2,AND(K6="SI",M6="%"),20),"")} | O6: =IFERROR(IF($M6="%", IF(N(N6)>1, N(N6)/100, N(N6)), IF(AND($J6>0,$M6="$"), N(N6)/$J6, "") ),"") | P6: =IFERROR(IF(M6="$", N(N6), IF(M6="%", J6*N(N6/100), "")), "") | Q6: =IF(J6="","",J6*(1-N(O6))) | R6: =IF(Q6="","",Q6/1.19) | T6: =IF(W6="","",IFERROR( IF(AND(ABS(N(W6))<0.5, BS6<=7), "Sin deuda", IF(AND(N(W6)>0, BS6<=7), "Con deuda", IF(AND(N(W6)>0, BS6>7), "Moroso", "") ) )," ")) | U6: =IF(R6="","",R6/2) | V6: =IF(AD6="","",SUM( IF(ISNUMBER(SEARCH("reserva",AD6)),AF6,0), IF(ISNUMBER(SEARCH("reserva",AH6)),AJ6,0), IF(ISNUMBER(SEARCH("reserva",AL6)),AN6,0), IF(ISNUMBER(SEARCH("reserva",AP6)),AR6,0), IF(ISNUMBER(SEARCH("reserva",AT6)),AV6,0) )) | W6: =IFERROR(U6-N(V6),"") | X6: =IF(W6="","",SUMIF($B$4:$B$1002,B6,$W$4:$W$1000)) | Y6: =IF(AB6="","",IFERROR( IF(AND(ABS(N(AB6))<0.5, BT6>=23), "Sin deuda", IF(AND(N(AB6)>0, BT6>=23), "Con deuda", IF(AND(N(AB6)>0, BT6<23), "Moroso", "") ) ),"")) | Z6: =IF(R6="","",R6/2) | AA6: =IF(AD6="","",SUM( IF(ISNUMBER(SEARCH("saldo",AD6)),AF6,0), IF(ISNUMBER(SEARCH("saldo",AH6)),AJ6,0), IF(ISNUMBER(SEARCH("saldo",AL6)),AN6,0), IF(ISNUMBER(SEARCH("saldo",AP6)),AR6,0), IF(ISNUMBER(SEARCH("saldo",AT6)),AV6,0) )) | AB6: =IFERROR(Z6-N(AA6),"") | AC6: =IF(AB6="","",SUMIF($B$4:$B$1002,B6,$AB$4:$AB$1000)) | BR6: =IF(E6="","",CONCATENATE(E6," ",F6," noches")) | BS6: =IF(G6="","",+TODAY()-G6) | BT6: =IF(H6="","",H6-TODAY())
A7: {=IF(B7="","","Grupo N˚"&SUMPRODUCT(($B$4:B7<>"")*($B$4:B7<>OFFSET($B$4,-1,0,ROWS($B$4:B7),1))))} | I7: =+IF(H7="","",G7+H7) | J7: =IFERROR(VLOOKUP(BR7,Pricing!$D$3:$E$58,2,FALSE),"") | N7: {=IFERROR(_xlfn.IFS((AND(K7="SI",M7="$")),J7*0.2,AND(K7="SI",M7="%"),20),"")} | O7: =IFERROR(IF($M7="%", IF(N(N7)>1, N(N7)/100, N(N7)), IF(AND($J7>0,$M7="$"), N(N7)/$J7, "") ),"") | P7: =IFERROR(IF(M7="$", N(N7), IF(M7="%", J7*N(N7/100), "")), "") | Q7: =IF(J7="","",J7*(1-N(O7))) | R7: =IF(Q7="","",Q7/1.19) | T7: =IF(W7="","",IFERROR( IF(AND(ABS(N(W7))<0.5, BS7<=7), "Sin deuda", IF(AND(N(W7)>0, BS7<=7), "Con deuda", IF(AND(N(W7)>0, BS7>7), "Moroso", "") ) )," ")) | U7: =IF(R7="","",R7/2) | V7: =IF(AD7="","",SUM( IF(ISNUMBER(SEARCH("reserva",AD7)),AF7,0), IF(ISNUMBER(SEARCH("reserva",AH7)),AJ7,0), IF(ISNUMBER(SEARCH("reserva",AL7)),AN7,0), IF(ISNUMBER(SEARCH("reserva",AP7)),AR7,0), IF(ISNUMBER(SEARCH("reserva",AT7)),AV7,0) )) | W7: =IFERROR(U7-N(V7),"") | X7: =IF(W7="","",SUMIF($B$4:$B$1002,B7,$W$4:$W$1000)) | Y7: =IF(AB7="","",IFERROR( IF(AND(ABS(N(AB7))<0.5, BT7>=23), "Sin deuda", IF(AND(N(AB7)>0, BT7>=23), "Con deuda", IF(AND(N(AB7)>0, BT7<23), "Moroso", "") ) ),"")) | Z7: =IF(R7="","",R7/2) | AA7: =IF(AD7="","",SUM( IF(ISNUMBER(SEARCH("saldo",AD7)),AF7,0), IF(ISNUMBER(SEARCH("saldo",AH7)),AJ7,0), IF(ISNUMBER(SEARCH("saldo",AL7)),AN7,0), IF(ISNUMBER(SEARCH("saldo",AP7)),AR7,0), IF(ISNUMBER(SEARCH("saldo",AT7)),AV7,0) )) | AB7: =IFERROR(Z7-N(AA7),"") | AC7: =IF(AB7="","",SUMIF($B$4:$B$1002,B7,$AB$4:$AB$1000)) | BR7: =IF(E7="","",CONCATENATE(E7," ",F7," noches")) | BS7: =IF(G7="","",+TODAY()-G7) | BT7: =IF(H7="","",H7-TODAY())
A8: {=IF(B8="","","Grupo N˚"&SUMPRODUCT(($B$4:B8<>"")*($B$4:B8<>OFFSET($B$4,-1,0,ROWS($B$4:B8),1))))} | I8: =+IF(H8="","",G8+H8) | J8: =IFERROR(VLOOKUP(BR8,Pricing!$D$3:$E$58,2,FALSE),"") | N8: {=IFERROR(_xlfn.IFS((AND(K8="SI",M8="$")),J8*0.2,AND(K8="SI",M8="%"),20),"")} | O8: =IFERROR(IF($M8="%", IF(N(N8)>1, N(N8)/100, N(N8)), IF(AND($J8>0,$M8="$"), N(N8)/$J8, "") ),"") | P8: =IFERROR(IF(M8="$", N(N8), IF(M8="%", J8*N(N8/100), "")), "") | Q8: =IF(J8="","",J8*(1-N(O8))) | R8: =IF(Q8="","",Q8/1.19) | T8: =IF(W8="","",IFERROR( IF(AND(ABS(N(W8))<0.5, BS8<=7), "Sin deuda", IF(AND(N(W8)>0, BS8<=7), "Con deuda", IF(AND(N(W8)>0, BS8>7), "Moroso", "") ) )," ")) | U8: =IF(R8="","",R8/2) | V8: =IF(AD8="","",SUM( IF(ISNUMBER(SEARCH("reserva",AD8)),AF8,0), IF(ISNUMBER(SEARCH("reserva",AH8)),AJ8,0), IF(ISNUMBER(SEARCH("reserva",AL8)),AN8,0), IF(ISNUMBER(SEARCH("reserva",AP8)),AR8,0), IF(ISNUMBER(SEARCH("reserva",AT8)),AV8,0) )) | W8: =IFERROR(U8-N(V8),"") | X8: =IF(W8="","",SUMIF($B$4:$B$1002,B8,$W$4:$W$1000)) | Y8: =IF(AB8="","",IFERROR( IF(AND(ABS(N(AB8))<0.5, BT8>=23), "Sin deuda", IF(AND(N(AB8)>0, BT8>=23), "Con deuda", IF(AND(N(AB8)>0, BT8<23), "Moroso", "") ) ),"")) | Z8: =IF(R8="","",R8/2) | AA8: =IF(AD8="","",SUM( IF(ISNUMBER(SEARCH("saldo",AD8)),AF8,0), IF(ISNUMBER(SEARCH("saldo",AH8)),AJ8,0), IF(ISNUMBER(SEARCH("saldo",AL8)),AN8,0), IF(ISNUMBER(SEARCH("saldo",AP8)),AR8,0), IF(ISNUMBER(SEARCH("saldo",AT8)),AV8,0) )) | AB8: =IFERROR(Z8-N(AA8),"") | AC8: =IF(AB8="","",SUMIF($B$4:$B$1002,B8,$AB$4:$AB$1000)) | BR8: =IF(E8="","",CONCATENATE(E8," ",F8," noches")) | BS8: =IF(G8="","",+TODAY()-G8) | BT8: =IF(H8="","",H8-TODAY())
A9: {=IF(B9="","","Grupo N˚"&SUMPRODUCT(($B$4:B9<>"")*($B$4:B9<>OFFSET($B$4,-1,0,ROWS($B$4:B9),1))))} | I9: =+IF(H9="","",G9+H9) | J9: =IFERROR(VLOOKUP(BR9,Pricing!$D$3:$E$58,2,FALSE),"") | N9: {=IFERROR(_xlfn.IFS((AND(K9="SI",M9="$")),J9*0.2,AND(K9="SI",M9="%"),20),"")} | O9: =IFERROR(IF($M9="%", IF(N(N9)>1, N(N9)/100, N(N9)), IF(AND($J9>0,$M9="$"), N(N9)/$J9, "") ),"") | P9: =IFERROR(IF(M9="$", N(N9), IF(M9="%", J9*N(N9/100), "")), "") | Q9: =IF(J9="","",J9*(1-N(O9))) | R9: =IF(Q9="","",Q9/1.19) | T9: =IF(W9="","",IFERROR( IF(AND(ABS(N(W9))<0.5, BS9<=7), "Sin deuda", IF(AND(N(W9)>0, BS9<=7), "Con deuda", IF(AND(N(W9)>0, BS9>7), "Moroso", "") ) )," ")) | U9: =IF(R9="","",R9/2) | V9: =IF(AD9="","",SUM( IF(ISNUMBER(SEARCH("reserva",AD9)),AF9,0), IF(ISNUMBER(SEARCH("reserva",AH9)),AJ9,0), IF(ISNUMBER(SEARCH("reserva",AL9)),AN9,0), IF(ISNUMBER(SEARCH("reserva",AP9)),AR9,0), IF(ISNUMBER(SEARCH("reserva",AT9)),AV9,0) )) | W9: =IFERROR(U9-N(V9),"") | X9: =IF(W9="","",SUMIF($B$4:$B$1002,B9,$W$4:$W$1000)) | Y9: =IF(AB9="","",IFERROR( IF(AND(ABS(N(AB9))<0.5, BT9>=23), "Sin deuda", IF(AND(N(AB9)>0, BT9>=23), "Con deuda", IF(AND(N(AB9)>0, BT9<23), "Moroso", "") ) ),"")) | Z9: =IF(R9="","",R9/2) | AA9: =IF(AD9="","",SUM( IF(ISNUMBER(SEARCH("saldo",AD9)),AF9,0), IF(ISNUMBER(SEARCH("saldo",AH9)),AJ9,0), IF(ISNUMBER(SEARCH("saldo",AL9)),AN9,0), IF(ISNUMBER(SEARCH("saldo",AP9)),AR9,0), IF(ISNUMBER(SEARCH("saldo",AT9)),AV9,0) )) | AB9: =IFERROR(Z9-N(AA9),"") | AC9: =IF(AB9="","",SUMIF($B$4:$B$1002,B9,$AB$4:$AB$1000)) | BR9: =IF(E9="","",CONCATENATE(E9," ",F9," noches")) | BS9: =IF(G9="","",+TODAY()-G9) | BT9: =IF(H9="","",H9-TODAY())
A10: {=IF(B10="","","Grupo N˚"&SUMPRODUCT(($B$4:B10<>"")*($B$4:B10<>OFFSET($B$4,-1,0,ROWS($B$4:B10),1))))} | I10: =+IF(H10="","",G10+H10) | J10: =IFERROR(VLOOKUP(BR10,Pricing!$D$3:$E$58,2,FALSE),"") | N10: {=IFERROR(_xlfn.IFS((AND(K10="SI",M10="$")),J10*0.2,AND(K10="SI",M10="%"),20),"")} | O10: =IFERROR(IF($M10="%", IF(N(N10)>1, N(N10)/100, N(N10)), IF(AND($J10>0,$M10="$"), N(N10)/$J10, "") ),"") | P10: =IFERROR(IF(M10="$", N(N10), IF(M10="%", J10*N(N10/100), "")), "") | Q10: =IF(J10="","",J10*(1-N(O10))) | R10: =IF(Q10="","",Q10/1.19) | T10: =IF(W10="","",IFERROR( IF(AND(ABS(N(W10))<0.5, BS10<=7), "Sin deuda", IF(AND(N(W10)>0, BS10<=7), "Con deuda", IF(AND(N(W10)>0, BS10>7), "Moroso", "") ) )," ")) | U10: =IF(R10="","",R10/2) | V10: =IF(AD10="","",SUM( IF(ISNUMBER(SEARCH("reserva",AD10)),AF10,0), IF(ISNUMBER(SEARCH("reserva",AH10)),AJ10,0), IF(ISNUMBER(SEARCH("reserva",AL10)),AN10,0), IF(ISNUMBER(SEARCH("reserva",AP10)),AR10,0), IF(ISNUMBER(SEARCH("reserva",AT10)),AV10,0) )) | W10: =IFERROR(U10-N(V10),"") | X10: =IF(W10="","",SUMIF($B$4:$B$1002,B10,$W$4:$W$1000)) | Y10: =IF(AB10="","",IFERROR( IF(AND(ABS(N(AB10))<0.5, BT10>=23), "Sin deuda", IF(AND(N(AB10)>0, BT10>=23), "Con deuda", IF(AND(N(AB10)>0, BT10<23), "Moroso", "") ) ),"")) | Z10: =IF(R10="","",R10/2) | AA10: =IF(AD10="","",SUM( IF(ISNUMBER(SEARCH("saldo",AD10)),AF10,0), IF(ISNUMBER(SEARCH("saldo",AH10)),AJ10,0), IF(ISNUMBER(SEARCH("saldo",AL10)),AN10,0), IF(ISNUMBER(SEARCH("saldo",AP10)),AR10,0), IF(ISNUMBER(SEARCH("saldo",AT10)),AV10,0) )) | AB10: =IFERROR(Z10-N(AA10),"") | AC10: =IF(AB10="","",SUMIF($B$4:$B$1002,B10,$AB$4:$AB$1000)) | BR10: =IF(E10="","",CONCATENATE(E10," ",F10," noches")) | BS10: =IF(G10="","",+TODAY()-G10) | BT10: =IF(H10="","",H10-TODAY())
A11: {=IF(B11="","","Grupo N˚"&SUMPRODUCT(($B$4:B11<>"")*($B$4:B11<>OFFSET($B$4,-1,0,ROWS($B$4:B11),1))))} | I11: =+IF(H11="","",G11+H11) | J11: =IFERROR(VLOOKUP(BR11,Pricing!$D$3:$E$58,2,FALSE),"") | N11: {=IFERROR(_xlfn.IFS((AND(K11="SI",M11="$")),J11*0.2,AND(K11="SI",M11="%"),20),"")} | O11: =IFERROR(IF($M11="%", IF(N(N11)>1, N(N11)/100, N(N11)), IF(AND($J11>0,$M11="$"), N(N11)/$J11, "") ),"") | P11: =IFERROR(IF(M11="$", N(N11), IF(M11="%", J11*N(N11/100), "")), "") | Q11: =IF(J11="","",J11*(1-N(O11))) | R11: =IF(Q11="","",Q11/1.19) | T11: =IF(W11="","",IFERROR( IF(AND(ABS(N(W11))<0.5, BS11<=7), "Sin deuda", IF(AND(N(W11)>0, BS11<=7), "Con deuda", IF(AND(N(W11)>0, BS11>7), "Moroso", "") ) )," ")) | U11: =IF(R11="","",R11/2) | V11: =IF(AD11="","",SUM( IF(ISNUMBER(SEARCH("reserva",AD11)),AF11,0), IF(ISNUMBER(SEARCH("reserva",AH11)),AJ11,0), IF(ISNUMBER(SEARCH("reserva",AL11)),AN11,0), IF(ISNUMBER(SEARCH("reserva",AP11)),AR11,0), IF(ISNUMBER(SEARCH("reserva",AT11)),AV11,0) )) | W11: =IFERROR(U11-N(V11),"") | X11: =IF(W11="","",SUMIF($B$4:$B$1002,B11,$W$4:$W$1000)) | Y11: =IF(AB11="","",IFERROR( IF(AND(ABS(N(AB11))<0.5, BT11>=23), "Sin deuda", IF(AND(N(AB11)>0, BT11>=23), "Con deuda", IF(AND(N(AB11)>0, BT11<23), "Moroso", "") ) ),"")) | Z11: =IF(R11="","",R11/2) | AA11: =IF(AD11="","",SUM( IF(ISNUMBER(SEARCH("saldo",AD11)),AF11,0), IF(ISNUMBER(SEARCH("saldo",AH11)),AJ11,0), IF(ISNUMBER(SEARCH("saldo",AL11)),AN11,0), IF(ISNUMBER(SEARCH("saldo",AP11)),AR11,0), IF(ISNUMBER(SEARCH("saldo",AT11)),AV11,0) )) | AB11: =IFERROR(Z11-N(AA11),"") | AC11: =IF(AB11="","",SUMIF($B$4:$B$1002,B11,$AB$4:$AB$1000)) | BR11: =IF(E11="","",CONCATENATE(E11," ",F11," noches")) | BS11: =IF(G11="","",+TODAY()-G11) | BT11: =IF(H11="","",H11-TODAY())
A12: {=IF(B12="","","Grupo N˚"&SUMPRODUCT(($B$4:B12<>"")*($B$4:B12<>OFFSET($B$4,-1,0,ROWS($B$4:B12),1))))} | I12: =+IF(H12="","",G12+H12) | J12: =IFERROR(VLOOKUP(BR12,Pricing!$D$3:$E$58,2,FALSE),"") | N12: {=IFERROR(_xlfn.IFS((AND(K12="SI",M12="$")),J12*0.2,AND(K12="SI",M12="%"),20),"")} | O12: =IFERROR(IF($M12="%", IF(N(N12)>1, N(N12)/100, N(N12)), IF(AND($J12>0,$M12="$"), N(N12)/$J12, "") ),"") | P12: =IFERROR(IF(M12="$", N(N12), IF(M12="%", J12*N(N12/100), "")), "") | Q12: =IF(J12="","",J12*(1-N(O12))) | R12: =IF(Q12="","",Q12/1.19) | T12: =IF(W12="","",IFERROR( IF(AND(ABS(N(W12))<0.5, BS12<=7), "Sin deuda", IF(AND(N(W12)>0, BS12<=7), "Con deuda", IF(AND(N(W12)>0, BS12>7), "Moroso", "") ) )," ")) | U12: =IF(R12="","",R12/2) | V12: =IF(AD12="","",SUM( IF(ISNUMBER(SEARCH("reserva",AD12)),AF12,0), IF(ISNUMBER(SEARCH("reserva",AH12)),AJ12,0), IF(ISNUMBER(SEARCH("reserva",AL12)),AN12,0), IF(ISNUMBER(SEARCH("reserva",AP12)),AR12,0), IF(ISNUMBER(SEARCH("reserva",AT12)),AV12,0) )) | W12: =IFERROR(U12-N(V12),"") | X12: =IF(W12="","",SUMIF($B$4:$B$1002,B12,$W$4:$W$1000)) | Y12: =IF(AB12="","",IFERROR( IF(AND(ABS(N(AB12))<0.5, BT12>=23), "Sin deuda", IF(AND(N(AB12)>0, BT12>=23), "Con deuda", IF(AND(N(AB12)>0, BT12<23), "Moroso", "") ) ),"")) | Z12: =IF(R12="","",R12/2) | AA12: =IF(AD12="","",SUM( IF(ISNUMBER(SEARCH("saldo",AD12)),AF12,0), IF(ISNUMBER(SEARCH("saldo",AH12)),AJ12,0), IF(ISNUMBER(SEARCH("saldo",AL12)),AN12,0), IF(ISNUMBER(SEARCH("saldo",AP12)),AR12,0), IF(ISNUMBER(SEARCH("saldo",AT12)),AV12,0) )) | AB12: =IFERROR(Z12-N(AA12),"") | AC12: =IF(AB12="","",SUMIF($B$4:$B$1002,B12,$AB$4:$AB$1000)) | BR12: =IF(E12="","",CONCATENATE(E12," ",F12," noches")) | BS12: =IF(G12="","",+TODAY()-G12) | BT12: =IF(H12="","",H12-TODAY())
A13: {=IF(B13="","","Grupo N˚"&SUMPRODUCT(($B$4:B13<>"")*($B$4:B13<>OFFSET($B$4,-1,0,ROWS($B$4:B13),1))))} | I13: =+IF(H13="","",G13+H13) | J13: =IFERROR(VLOOKUP(BR13,Pricing!$D$3:$E$58,2,FALSE),"") | N13: {=IFERROR(_xlfn.IFS((AND(K13="SI",M13="$")),J13*0.2,AND(K13="SI",M13="%"),20),"")} | O13: =IFERROR(IF($M13="%", IF(N(N13)>1, N(N13)/100, N(N13)), IF(AND($J13>0,$M13="$"), N(N13)/$J13, "") ),"") | P13: =IFERROR(IF(M13="$", N(N13), IF(M13="%", J13*N(N13/100), "")), "") | Q13: =IF(J13="","",J13*(1-N(O13))) | R13: =IF(Q13="","",Q13/1.19) | T13: =IF(W13="","",IFERROR( IF(AND(ABS(N(W13))<0.5, BS13<=7), "Sin deuda", IF(AND(N(W13)>0, BS13<=7), "Con deuda", IF(AND(N(W13)>0, BS13>7), "Moroso", "") ) )," ")) | U13: =IF(R13="","",R13/2) | V13: =IF(AD13="","",SUM( IF(ISNUMBER(SEARCH("reserva",AD13)),AF13,0), IF(ISNUMBER(SEARCH("reserva",AH13)),AJ13,0), IF(ISNUMBER(SEARCH("reserva",AL13)),AN13,0), IF(ISNUMBER(SEARCH("reserva",AP13)),AR13,0), IF(ISNUMBER(SEARCH("reserva",AT13)),AV13,0) )) | W13: =IFERROR(U13-N(V13),"") | X13: =IF(W13="","",SUMIF($B$4:$B$1002,B13,$W$4:$W$1000)) | Y13: =IF(AB13="","",IFERROR( IF(AND(ABS(N(AB13))<0.5, BT13>=23), "Sin deuda", IF(AND(N(AB13)>0, BT13>=23), "Con deuda", IF(AND(N(AB13)>0, BT13<23), "Moroso", "") ) ),"")) | Z13: =IF(R13="","",R13/2) | AA13: =IF(AD13="","",SUM( IF(ISNUMBER(SEARCH("saldo",AD13)),AF13,0), IF(ISNUMBER(SEARCH("saldo",AH13)),AJ13,0), IF(ISNUMBER(SEARCH("saldo",AL13)),AN13,0), IF(ISNUMBER(SEARCH("saldo",AP13)),AR13,0), IF(ISNUMBER(SEARCH("saldo",AT13)),AV13,0) )) | AB13: =IFERROR(Z13-N(AA13),"") | AC13: =IF(AB13="","",SUMIF($B$4:$B$1002,B13,$AB$4:$AB$1000)) | BR13: =IF(E13="","",CONCATENATE(E13," ",F13," noches")) | BS13: =IF(G13="","",+TODAY()-G13) | BT13: =IF(H13="","",H13-TODAY())
A14: {=IF(B14="","","Grupo N˚"&SUMPRODUCT(($B$4:B14<>"")*($B$4:B14<>OFFSET($B$4,-1,0,ROWS($B$4:B14),1))))} | I14: =+IF(H14="","",G14+H14) | J14: =IFERROR(VLOOKUP(BR14,Pricing!$D$3:$E$58,2,FALSE),"") | N14: {=IFERROR(_xlfn.IFS((AND(K14="SI",M14="$")),J14*0.2,AND(K14="SI",M14="%"),20),"")} | O14: =IFERROR(IF($M14="%", IF(N(N14)>1, N(N14)/100, N(N14)), IF(AND($J14>0,$M14="$"), N(N14)/$J14, "") ),"") | P14: =IFERROR(IF(M14="$", N(N14), IF(M14="%", J14*N(N14/100), "")), "") | Q14: =IF(J14="","",J14*(1-N(O14))) | R14: =IF(Q14="","",Q14/1.19) | T14: =IF(W14="","",IFERROR( IF(AND(ABS(N(W14))<0.5, BS14<=7), "Sin deuda", IF(AND(N(W14)>0, BS14<=7), "Con deuda", IF(AND(N(W14)>0, BS14>7), "Moroso", "") ) )," ")) | U14: =IF(R14="","",R14/2) | V14: =IF(AD14="","",SUM( IF(ISNUMBER(SEARCH("reserva",AD14)),AF14,0), IF(ISNUMBER(SEARCH("reserva",AH14)),AJ14,0), IF(ISNUMBER(SEARCH("reserva",AL14)),AN14,0), IF(ISNUMBER(SEARCH("reserva",AP14)),AR14,0), IF(ISNUMBER(SEARCH("reserva",AT14)),AV14,0) )) | W14: =IFERROR(U14-N(V14),"") | X14: =IF(W14="","",SUMIF($B$4:$B$1002,B14,$W$4:$W$1000)) | Y14: =IF(AB14="","",IFERROR( IF(AND(ABS(N(AB14))<0.5, BT14>=23), "Sin deuda", IF(AND(N(AB14)>0, BT14>=23), "Con deuda", IF(AND(N(AB14)>0, BT14<23), "Moroso", "") ) ),"")) | Z14: =IF(R14="","",R14/2) | AA14: =IF(AD14="","",SUM( IF(ISNUMBER(SEARCH("saldo",AD14)),AF14,0), IF(ISNUMBER(SEARCH("saldo",AH14)),AJ14,0), IF(ISNUMBER(SEARCH("saldo",AL14)),AN14,0), IF(ISNUMBER(SEARCH("saldo",AP14)),AR14,0), IF(ISNUMBER(SEARCH("saldo",AT14)),AV14,0) )) | AB14: =IFERROR(Z14-N(AA14),"") | AC14: =IF(AB14="","",SUMIF($B$4:$B$1002,B14,$AB$4:$AB$1000)) | BR14: =IF(E14="","",CONCATENATE(E14," ",F14," noches")) | BS14: =IF(G14="","",+TODAY()-G14) | BT14: =IF(H14="","",H14-TODAY())
A15: {=IF(B15="","","Grupo N˚"&SUMPRODUCT(($B$4:B15<>"")*($B$4:B15<>OFFSET($B$4,-1,0,ROWS($B$4:B15),1))))} | I15: =+IF(H15="","",G15+H15) | J15: =IFERROR(VLOOKUP(BR15,Pricing!$D$3:$E$58,2,FALSE),"") | N15: {=IFERROR(_xlfn.IFS((AND(K15="SI",M15="$")),J15*0.2,AND(K15="SI",M15="%"),20),"")} | O15: =IFERROR(IF($M15="%", IF(N(N15)>1, N(N15)/100, N(N15)), IF(AND($J15>0,$M15="$"), N(N15)/$J15, "") ),"") | P15: =IFERROR(IF(M15="$", N(N15), IF(M15="%", J15*N(N15/100), "")), "") | Q15: =IF(J15="","",J15*(1-N(O15))) | R15: =IF(Q15="","",Q15/1.19) | T15: =IF(W15="","",IFERROR( IF(AND(ABS(N(W15))<0.5, BS15<=7), "Sin deuda", IF(AND(N(W15)>0, BS15<=7), "Con deuda", IF(AND(N(W15)>0, BS15>7), "Moroso", "") ) )," ")) | U15: =IF(R15="","",R15/2) | V15: =IF(AD15="","",SUM( IF(ISNUMBER(SEARCH("reserva",AD15)),AF15,0), IF(ISNUMBER(SEARCH("reserva",AH15)),AJ15,0), IF(ISNUMBER(SEARCH("reserva",AL15)),AN15,0), IF(ISNUMBER(SEARCH("reserva",AP15)),AR15,0), IF(ISNUMBER(SEARCH("reserva",AT15)),AV15,0) )) | W15: =IFERROR(U15-N(V15),"") | X15: =IF(W15="","",SUMIF($B$4:$B$1002,B15,$W$4:$W$1000)) | Y15: =IF(AB15="","",IFERROR( IF(AND(ABS(N(AB15))<0.5, BT15>=23), "Sin deuda", IF(AND(N(AB15)>0, BT15>=23), "Con deuda", IF(AND(N(AB15)>0, BT15<23), "Moroso", "") ) ),"")) | Z15: =IF(R15="","",R15/2) | AA15: =IF(AD15="","",SUM( IF(ISNUMBER(SEARCH("saldo",AD15)),AF15,0), IF(ISNUMBER(SEARCH("saldo",AH15)),AJ15,0), IF(ISNUMBER(SEARCH("saldo",AL15)),AN15,0), IF(ISNUMBER(SEARCH("saldo",AP15)),AR15,0), IF(ISNUMBER(SEARCH("saldo",AT15)),AV15,0) )) | AB15: =IFERROR(Z15-N(AA15),"") | AC15: =IF(AB15="","",SUMIF($B$4:$B$1002,B15,$AB$4:$AB$1000)) | BR15: =IF(E15="","",CONCATENATE(E15," ",F15," noches")) | BS15: =IF(G15="","",+TODAY()-G15) | BT15: =IF(H15="","",H15-TODAY())
... A1002: {=IF(B1002="","","Grupo N˚"&SUMPRODUCT(($B$4:B1002<>"")*($B$4:B1002<>OFFSET($B$4,-1,0,ROWS($B$4:B1002),1))))} | I1002: =+IF(H1002="","",G1002+H1002) | J1002: =IFERROR(VLOOKUP(BR1002,Pricing!$D$3:$E$58,2,FALSE),"") | N1002: {=IFERROR(_xlfn.IFS((AND(K1002="SI",M1002="$")),J1002*0.2,AND(K1002="SI",M1002="%"),20),"")} | O1002: =IFERROR(IF($M1002="%", IF(N(N1002)>1, N(N1002)/100, N(N1002)), IF(AND($J1002>0,$M1002="$"), N(N1002)/$J1002, "") ),"") | P1002: =IFERROR(IF(M1002="$", N(N1002), IF(M1002="%", J1002*N(N1002/100), "")), "") | Q1002: =IF(J1002="","",J1002*(1-N(O1002))) | R1002: =IF(Q1002="","",Q1002/1.19) | T1002: =IF(W1002="","",IFERROR( IF(AND(ABS(N(W1002))<0.5, BS1002<=7), "Sin deuda", IF(AND(N(W1002)>0, BS1002<=7), "Con deuda", IF(AND(N(W1002)>0, BS1002>7), "Moroso", "") ) )," ")) | U1002: =IF(R1002="","",R1002/2) | V1002: =IF(AD1002="","",SUM( IF(ISNUMBER(SEARCH("reserva",AD1002)),AF1002,0), IF(ISNUMBER(SEARCH("reserva",AH1002)),AJ1002,0), IF(ISNUMBER(SEARCH("reserva",AL1002)),AN1002,0), IF(ISNUMBER(SEARCH("reserva",AP1002)),AR1002,0), IF(ISNUMBER(SEARCH("reserva",AT1002)),AV1002,0) )) | W1002: =IFERROR(U1002-N(V1002),"") | X1002: =IF(W1002="","",SUMIF($B$4:$B$1002,B1002,$W$4:$W$1000)) | Y1002: =IF(AB1002="","",IFERROR( IF(AND(ABS(N(AB1002))<0.5, BT1002>=23), "Sin deuda", IF(AND(N(AB1002)>0, BT1002>=23), "Con deuda", IF(AND(N(AB1002)>0, BT1002<23), "Moroso", "") ) ),"")) | Z1002: =IF(R1002="","",R1002/2) | AA1002: =IF(AD1002="","",SUM( IF(ISNUMBER(SEARCH("saldo",AD1002)),AF1002,0), IF(ISNUMBER(SEARCH("saldo",AH1002)),AJ1002,0), IF(ISNUMBER(SEARCH("saldo",AL1002)),AN1002,0), IF(ISNUMBER(SEARCH("saldo",AP1002)),AR1002,0), IF(ISNUMBER(SEARCH("saldo",AT1002)),AV1002,0) )) | AB1002: =IFERROR(Z1002-N(AA1002),"") | AC1002: =IF(AB1002="","",SUMIF($B$4:$B$1002,B1002,$AB$4:$AB$1000)) | BR1002: =IF(E1002="","",CONCATENATE(E1002," ",F1002," noches")) | BS1002: =IF(G1002="","",+TODAY()-G1002) | BT1002: =IF(H1002="","",H1002-TODAY())
A1003: X | B1003: X | C1003: X | D1003: X | E1003: X | F1003: X | G1003: X | H1003: X | I1003: X | J1003: X | K1003: X | L1003: X | M1003: X | N1003: X | O1003: X | P1003: X | Q1003: X | R1003: X | T1003: X | U1003: X | V1003: X | W1003: =IFERROR(U1003-N(V1003),"") | X1003: =IF(W1003="","",SUMIF($B$4:$B$1002,B1003,$W$4:$W$1000)) | Y1003: =IF(AB1003="","",IFERROR( IF(AND(ABS(N(AB1003))<0.5, BT1003>=23), "Sin deuda", IF(AND(N(AB1003)>0, BT1003>=23), "Con deuda", IF(AND(N(AB1003)>0, BT1003<23), "Moroso", "") ) ),"")) | Z1003: X | AA1003: X | AB1003: =IFERROR(Z1003-N(AA1003),"") | AC1003: X | AD1003: X | AE1003: X | AF1003: X | AG1003: X | AH1003: X | AI1003: X | AJ1003: X | AK1003: X | AL1003: X | AM1003: X | AN1003: X | AO1003: X | AP1003: X | AQ1003: X | AR1003: X | AS1003: X | AT1003: X | AU1003: X | AV1003: X | AW1003: X | BR1003: x | BS1003: =IF(G1003="","",+TODAY()-G1003) -> #VALUE! | BT1003: =IF(H1003="","",H1003-TODAY()) -> #VALUE!

Sheet Mantenedor
A1: N˚ | B1: Programa | C1: Moneda | D1: V˚B˚ | E1: Descuento | F1: Estado_reserva | G1: Estado_saldo | H1: Operador | I1: Medio de pago | J1: Fecha de reserva
A2: 0 | B2: Baker Single | C2: CLP | D2: Sin descuento | E2: 0 | F2: Sin deuda | G2: Sin deuda | H2: NO | I2: Transferencia | J2: =+TODAY() -> 45947 | K2: % | L2: Reserva
A3: 1 | B3: Baker Full | C3: USD | D3: FSN | E3: 0.01 | F3: Deuda | G3: Deuda | H3: SI | I3: WebPay | K3: $ | L3: Saldo
A4: 2 | B4: Non Angler | D4: JIP | E4: 0.02 | F4: Moroso | G4: Moroso
A5: 3 | E5: 0.03
A6: 4 | E6: 0.04
A7: 5 | E7: 0.05
A8: 6 | E8: 0.06
A9: 7 | E9: 0.07
A10: 8 | E10: 0.08
A11: 9 | E11: 0.09
A12: 10 | E12: 0.1
A13: 11 | E13: 0.11
A14: 12 | E14: 0.12
A15: 13 | E15: 0.13
A16: 14 | E16: 0.14
... A27: 25 | E27: 0.25
A28: 26
A29: 27
A30: 28
A31: 29
A32: 30
A33: 31
A34: 32
A35: 33
A36: 34
A37: 35
A38: 36
A39: 37
... A52: 50

Sheet Políticas
A1: Políticas GBL
A3: 1. Políticas de pago
A4: 1.1 Política de pago: Reserva
A5: El pago de la reserva debe ser realizado hasta 7 días posterior realizada la reserva
A7: 1.2 Política de pago: Saldo
A8: El pago del saldo debe ser realizado hasta 23 días antes del check in
A14: 2. Clasificación de deudores
A15: 1. Al día: | B15: Cliente pago la totalidad de la reserva y del saldo a la fecha
A16: 2. Debe_reserva: | B16: Cliente no ha cancelado la totalidad del monto de la reserva pero no han pasado 7 días desde la fecha de reserva
A17: 3. Debe_saldo: | B17: Cliente no ha cancelado la totalidad del monto del saldo pero faltan más de 23 días para el check-in
A18: 4. Moroso_reserva: | B18: Cliente no ha cancelado la totalidad del monto de la reserva y ya han pasadomás de 7 días desde la fecha de reserva
A19: 5. Moroso_saldo: | B19: Cliente no ha cancelado la totalidad del monto del saldo y faltan menos de 23 días para el check-in
A21: 3. Política de descuento
A22: 3.1 Aprobación: | B22: Solo y únicamente Franz Schee l (FSN) y Jorge Icaza (JIP) están autorizados para aprobar un descuento | J22: *Clave para desbloquear descuentos
A23: 3.2 Rangos: | B23: Se podrán aplicar descuentos como máximo de un 25% sobre el precio lista
A24: 3.3 Operadores | B24: El descuento asociado a operadores es de un 20% del precio lista
A25: 3.4 Descuento Usuario/Operador | B25: No se podrán aplicar descuento_usuarios a pasajeros que vengan por operadores

Sheet Pricing
A1: PRICING PESCA: NACIONAL | G1: PRICING PESCA: EXTRANJERO
A2: BASE | B2: N˚ DÍAS | C2: N˚ NOCHES | D2: TEXTO | E2: VALOR BRUTO (CLP) | G2: BASE | H2: N˚ DÍAS | I2: N˚ NOCHES | J2: TEXTO | K2: VALOR BRUTO (USD)
A3: Baker single | B3: 1 | C3: 1 noche | D3: =+CONCATENATE(A3," ",C3) -> Baker single 1 noche | E3: 770000 | G3: Base single | H3: 1 | I3: 1 noche | J3: Base single 1 noche | K3: 1890
A4: Baker full | B4: 1 | C4: 1 noche | D4: =+CONCATENATE(A4," ",C4) -> Baker full 1 noche | E4: 550000 | G4: Base doble | H4: 1 | I4: 1 noche | J4: Base doble 1 noche | K4: 1350
A5: Non Angler | B5: 1 | C5: 1 noche | D5: =+CONCATENATE(A5," ",C5) -> Non Angler 1 noche | E5: 550000 | G5: Non angler nacional | H5: 1 | I5: 1 noche | J5: Non angler nacional 1 noche | K5: 945
A6: Baker single | B6: =+B3+1 -> 2 | C6: 2 noches | D6: =+CONCATENATE(A6," ",C6) -> Baker single 2 noches | E6: 1330000 | G6: Base single | H6: 2 | I6: 2 noches | J6: Base single 2 noches | K6: 3150
A7: Baker full | B7: =+B4+1 -> 2 | C7: 2 noches | D7: =+CONCATENATE(A7," ",C7) -> Baker full 2 noches | E7: 950000 | G7: Base doble | H7: 2 | I7: 2 noches | J7: Base doble 2 noches | K7: 2250
A8: Non Angler | B8: =+B5+1 -> 2 | C8: 2 noches | D8: =+CONCATENATE(A8," ",C8) -> Non Angler 2 noches | E8: 950000 | G8: Non angler nacional | H8: 2 | I8: 2 noches | J8: Non angler nacional 2 noches | K8: 1575
A9: Baker single | B9: =+B6+1 -> 3 | C9: 3 noches | D9: =+CONCATENATE(A9," ",C9) -> Baker single 3 noches | E9: 1890000 | G9: Base single | H9: 3 | I9: 3 noches | J9: Base single 3 noches | K9: 4410
A10: Baker full | B10: =+B7+1 -> 3 | C10: 3 noches | D10: =+CONCATENATE(A10," ",C10) -> Baker full 3 noches | E10: 1350000 | G10: Base doble | H10: 3 | I10: 3 noches | J10: Base doble 3 noches | K10: 3150
A11: Non Angler | B11: =+B8+1 -> 3 | C11: 3 noches | D11: =+CONCATENATE(A11," ",C11) -> Non Angler 3 noches | E11: 1350000 | G11: Non angler nacional | H11: 3 | I11: 3 noches | J11: Non angler nacional 3 noches | K11: 2205
A12: Baker single | B12: =+B9+1 -> 4 | C12: 4 noches | D12: =+CONCATENATE(A12," ",C12) -> Baker single 4 noches | E12: 2450000 | G12: Base single | H12: 4 | I12: 4 noches | J12: Base single 4 noches | K12: 5670
A13: Baker full | B13: =+B10+1 -> 4 | C13: 4 noches | D13: =+CONCATENATE(A13," ",C13) -> Baker full 4 noches | E13: 1750000 | G13: Base doble | H13: 4 | I13: 4 noches | J13: Base doble 4 noches | K13: 4050
A14: Non Angler | B14: =+B11+1 -> 4 | C14: 4 noches | D14: =+CONCATENATE(A14," ",C14) -> Non Angler 4 noches | E14: 1750000 | G14: Non angler nacional | H14: 4 | I14: 4 noches | J14: Non angler nacional 4 noches | K14: 2835
A15: Baker single | B15: =+B12+1 -> 5 | C15: 5 noches | D15: =+CONCATENATE(A15," ",C15) -> Baker single 5 noches | E15: 3010000 | G15: Base single | H15: 5 | I15: 5 noches | J15: Base single 5 noches | K15: 6930
A16: Baker full | B16: =+B13+1 -> 5 | C16: 5 noches | D16: =+CONCATENATE(A16," ",C16) -> Baker full 5 noches | E16: 2150000 | G16: Base doble | H16: 5 | I16: 5 noches | J16: Base doble 5 noches | K16: 4950
A17: Non Angler | B17: =+B14+1 -> 5 | C17: 5 noches | D17: =+CONCATENATE(A17," ",C17) -> Non Angler 5 noches | E17: 2150000 | G17: Non angler nacional | H17: 5 | I17: 5 noches | J17: Non angler nacional 5 noches | K17: 3465
... A44: Non Angler | B44: =+B41+1 -> 14 | C44: 14 noches | D44: =+CONCATENATE(A44," ",C44) -> Non Angler 14 noches | E44: 5750000 | G44: Non angler nacional | H44: 14 | I44: 14 noches | J44: Non angler nacional 14 noches | K44: 9135
A45: Host | B45: 1 | C45: 1 noche | D45: =+CONCATENATE(A45," ",C45) -> Host 1 noche | E45: 0 | G45: Host | H45: 1 | I45: 1 noche | J45: Host 1 noche | K45: 0
A46: Host | B46: 2 | C46: 2 Noches | D46: =+CONCATENATE(A46," ",C46) -> Host 2 Noches | E46: 0 | G46: Host | H46: 2 | I46: 2 Noches | J46: Host 2 Noches | K46: 0
A47: Host | B47: 3 | C47: 3 Noches | D47: =+CONCATENATE(A47," ",C47) -> Host 3 Noches | E47: 0 | G47: Host | H47: 3 | I47: 3 Noches | J47: Host 3 Noches | K47: 0
A48: Host | B48: 4 | C48: 4 Noches | D48: =+CONCATENATE(A48," ",C48) -> Host 4 Noches | E48: 0 | G48: Host | H48: 4 | I48: 4 Noches | J48: Host 4 Noches | K48: 0
A49: Host | B49: 5 | C49: 5 Noches | D49: =+CONCATENATE(A49," ",C49) -> Host 5 Noches | E49: 0 | G49: Host | H49: 5 | I49: 5 Noches | J49: Host 5 Noches | K49: 0
A50: Host | B50: 6 | C50: 6 Noches | D50: =+CONCATENATE(A50," ",C50) -> Host 6 Noches | E50: 0 | G50: Host | H50: 6 | I50: 6 Noches | J50: Host 6 Noches | K50: 0
A51: Host | B51: 7 | C51: 7 Noches | D51: =+CONCATENATE(A51," ",C51) -> Host 7 Noches | E51: 0 | G51: Host | H51: 7 | I51: 7 Noches | J51: Host 7 Noches | K51: 0
A52: Host | B52: 8 | C52: 8 Noches | D52: =+CONCATENATE(A52," ",C52) -> Host 8 Noches | E52: 0 | G52: Host | H52: 8 | I52: 8 Noches | J52: Host 8 Noches | K52: 0
A53: Host | B53: 9 | C53: 9 Noches | D53: =+CONCATENATE(A53," ",C53) -> Host 9 Noches | E53: 0 | G53: Host | H53: 9 | I53: 9 Noches | J53: Host 9 Noches | K53: 0
A54: Host | B54: 10 | C54: 10 Noches | D54: =+CONCATENATE(A54," ",C54) -> Host 10 Noches | E54: 0 | G54: Host | H54: 10 | I54: 10 Noches | J54: Host 10 Noches | K54: 0
A55: Host | B55: 11 | C55: 11 Noches | D55: =+CONCATENATE(A55," ",C55) -> Host 11 Noches | E55: 0 | G55: Host | H55: 11 | I55: 11 Noches | J55: Host 11 Noches | K55: 0
A56: Host | B56: 12 | C56: 12 Noches | D56: =+CONCATENATE(A56," ",C56) -> Host 12 Noches | E56: 0 | G56: Host | H56: 12 | I56: 12 Noches | J56: Host 12 Noches | K56: 0
... A58: Host | B58: 14 | C58: 14 Noches | D58: =+CONCATENATE(A58," ",C58) -> Host 14 Noches | E58: 0 | G58: Host | H58: 14 | I58: 14 Noches | J58: Host 14 Noches | K58: 0
